mucklas/__init__.py
mucklas/dataclasses.py
mucklas/skeleton.py
mucklas-0.2.1.dist-info/LICENSE.txt
mucklas-0.2.1.dist-info/METADATA
mucklas-0.2.1.dist-info/WHEEL
mucklas-0.2.1.dist-info/top_level.txt
mucklas-0.2.1.dist-info/RECORD
