Metadata-Version: 2.2
Name: mucklas
Version: 0.2.1
Summary: A collection of useful (Python) functions and concepts. Something you can discover if you look closely - just like the fictional creatures of the same name in Sven Nordqvist's Swedish books 'Pettson och Findus'.
Home-page: https://github.com/LukasGold/mucklas
Author: Lukas Gold
Author-email: lukas.gold@isc.fraunhofer.de
License: AGPL-3.0-or-later
Project-URL: Documentation, https://github.com/LukasGold/mucklas
Project-URL: Source, https://github.com/LukasGold/mucklas
Platform: any
Classifier: Development Status :: 4 - Beta
Classifier: Programming Language :: Python
Requires-Python: >=3.8
License-File: LICENSE.txt
Requires-Dist: backports.strenum; python_version < "3.11"
Requires-Dist: pydantic
Requires-Dist: sphinx
Provides-Extra: dev
Requires-Dist: pre-commit; extra == "dev"
Requires-Dist: tox; extra == "dev"
Provides-Extra: testing
Requires-Dist: setuptools; extra == "testing"
Requires-Dist: pytest; extra == "testing"
Requires-Dist: pytest-cov; extra == "testing"
